cite/__init__.py
cite/_version.py
cite-0.7.2.dist-info/LICENSE
cite-0.7.2.dist-info/METADATA
cite-0.7.2.dist-info/WHEEL
cite-0.7.2.dist-info/entry_points.txt
cite-0.7.2.dist-info/top_level.txt
cite-0.7.2.dist-info/RECORD
