Metadata-Version: 2.1
Name: cite
Version: 0.7.2
Summary: Command line tool to turn DOIs into citations
Home-page: https://github.com/rgieseke/cite
Author: Robert Gieseke
Author-email: rob.g@web.de
License: BSD
Platform: UNKNOWN
Classifier: Development Status :: 4 - Beta
Classifier: Intended Audience :: Developers
Classifier: Operating System :: OS Independent
Classifier: Programming Language :: Python :: 3.6
Classifier: Programming Language :: Python :: 3.7
Classifier: Programming Language :: Python :: 3.8
